bitteragent/__init__.py
bitteragent/__main__.py
bitteragent/agent.py
bitteragent/tools.py
bitteragent/adapters/__init__.py
bitteragent/adapters/anthropic.py
bitteragent/adapters/base.py
bitteragent/native_tools/__init__.py
bitteragent/native_tools/base.py
bitteragent/native_tools/file_ops.py
bitteragent/native_tools/shell.py
bitteragent/providers/__init__.py
bitteragent/providers/anthropic.py
bitteragent/providers/base.py
bitteragent-0.1.1.dist-info/METADATA
bitteragent-0.1.1.dist-info/WHEEL
bitteragent-0.1.1.dist-info/entry_points.txt
bitteragent-0.1.1.dist-info/top_level.txt
bitteragent-0.1.1.dist-info/RECORD
