Metadata-Version: 2.4
Name: bitteragent
Version: 0.1.1
Summary: Minimal Python CLI agent with native tools for shell execution and file operations
Author-email: Alice Hau <alice.a.hau@gmail.com>
License-Expression: MIT
Project-URL: Homepage, https://github.com/alicehau/bitteragent
Project-URL: Repository, https://github.com/alicehau/bitteragent
Project-URL: Issues, https://github.com/alicehau/bitteragent/issues
Classifier: Development Status :: 3 - Alpha
Classifier: Intended Audience :: Developers
Classifier: Programming Language :: Python :: 3
Classifier: Programming Language :: Python :: 3.12
Requires-Python: >=3.12
Requires-Dist: click
Requires-Dist: python-dotenv
Requires-Dist: anthropic
Provides-Extra: dev
Requires-Dist: terminal-bench>=0.2.17; extra == "dev"
